{
    "myBudget" :[
        {
            "title": "Eat out",
            "budget": 30
        },
        {
            "title": "Rent",
            "budget": 350
        },
        {
            "title": "Groceries",
            "budget": 90
        },
        {
            "title": "Electricity",
            "budget": 55
        },
        {
            "title": "Shopping",
            "budget": 100
        },
        {
            "title": "Car Issues",
            "budget": 200
        },
        {
            "title": "Trips",
            "budget": "400"
        }
    ]
}